detoxifier/__init__.py
detoxifier/config.py
detoxifier/main.py
detoxifier-0.2.dist-info/LICENSE.txt
detoxifier-0.2.dist-info/METADATA
detoxifier-0.2.dist-info/WHEEL
detoxifier-0.2.dist-info/top_level.txt
detoxifier-0.2.dist-info/RECORD
