Metadata-Version: 2.1
Name: detoxifier
Version: 0.2
Summary: Detoxifier library identifies toxic words in a query and detoxified it by replacing toxic words.
Home-page: UNKNOWN
Author: Sukanthen.SS
Author-email: sukanthen1999@gmail.com
License: UNKNOWN
Platform: UNKNOWN
Classifier: Programming Language :: Python :: 3
Classifier: License :: OSI Approved :: MIT License
Classifier: Operating System :: OS Independent
License-File: LICENSE.txt
Requires-Dist: flashtext (==2.7)
